LICENSE.txt
setup.py
makarenko_serializer/__init__.py
makarenko_serializer/__main__.py
makarenko_serializer/constants.py
makarenko_serializer/encoder.py
makarenko_serializer/help_funcs.py
makarenko_serializer/json_serializer.py
makarenko_serializer/makarenko_serializer.py
makarenko_serializer/serializer.py
makarenko_serializer/xml_serializer.py
makarenko_serializer.egg-info/PKG-INFO
makarenko_serializer.egg-info/SOURCES.txt
makarenko_serializer.egg-info/dependency_links.txt
makarenko_serializer.egg-info/entry_points.txt
makarenko_serializer.egg-info/top_level.txt