Metadata-Version: 2.1
Name: makarenko-serializer
Version: 0.1.0
Summary: json/xml serializer
Home-page: UNKNOWN
Author: alyona makarenko
Author-email: alyonka.m.by@gmail.com
License: MIT
Platform: UNKNOWN
License-File: LICENSE.txt
